{
    "SKU466789": {
      "name": "Шампунь питательный",
      "cost": 300,
      "category": "Шампунь",
      "description": "Мягкий шампунь на основе кератина обладает высоким увлажняющим и кондиционирующим эффектом . Придает волосам  послушность , блеск и объем. Шампунь имеет лёгкий аромат цитрусовых.",
      "volume": "250мл",
      "brand" : "RevlonProfessional",
      "producer": "Испания",
      "show": 1,
      "availability": 2,
      "img":"img/revlon-professional-200ml.jpg"
    },
    "SKU1015": {
      "name": "Шампунь для густых волос",
      "cost": 426,
      "category": "Шампунь",
      "description": "Шампунь  преображает сухие волосы, придает им гладкость, яркость и блеск. Обеспечивает максимальную защиту в сохранение цвета  окрашенных волос.",
      "volume": "250мл",
      "brand" : "RevlonProfessional",
      "producer": "Испания",
      "show": 1,
      "availability": 3,
      "img":"img/Revlon-Revlon-250ml.jpg"
    },
    "SKU2525": {
      "name": "Шампунь для ломких волос",
      "cost": 285,
      "category": "Шампунь",
      "description": "Шампунь для восстановления сухих , химически поврежденных волос . Шампунь придает волосам эластичность и жизненную силу. Волосы становятся мягкими , более послушными и блестящими.",
      "volume": "350мл",
      "brand" : "RevlonProfessional",
      "producer": "Испания",
      "show": 1,
      "availability": 4,
      "img":"img/shampoo-cab-pro.jpg"
    },
    "SKU67": {
      "name": "Масло Люкс Оил",
      "cost": 770,
      "category": "Масло",
      "description": "Легкое масло- эликсир придает волосам блеск и сияние, устраняет пушистость волос, защищает волосы от ломкости и сечения.Масло не перегружает волосы, не оставляет жирного блеска на волосах и липкости. Имеет приятный аромат.",
      "volume": "100мл",
      "brand" : "WellaProfessional",
      "producer": "Германия",
      "show": 1,
      "availability": 5,
      "img":"img/res.jpg"
    },
    "SKU1304": {
      "name": "Кондиционер разглаживающий",
      "cost": 220,
      "category": "Маска",
      "description": "Маска-уход для увлажнения и питания вьющихся волос, делает волосы более сильными, эластичными и блестящими, локоны приобретают более четкую форму.",
      "volume": "201мл",
      "brand" : "Berrywell",
      "producer": "Германия",
      "show": 1,
      "availability": "2",
      "img":"img/green.jpg"
    },
    "SKU 1": {
      "name": "Кондиционер для темных волос",
      "cost": 290,
      "category": "Кондиционер",
      "description": "Кондиционер для темных волос придаёт волосам больше массы, при этом не утяжеляет их. Волосы остаются легкими и подвижными. Волосы после использования кондиционера приобретают больше гладкости и блеска. Имеет приятный парфюмированный аромат.",
      "volume": "250мл",
      "brand" : "MadesCosmetics",
      "producer": "Нидерландах",
      "show": 1,
      "availability": "2",
      "img":"img/mades-cosmetics.jpg"
    }
  
  }